sosfilt/__init__.py
sosfilt/_sosfilt.cpython-314-x86_64-linux-gnu.so
sosfilt/_zpk_funcs.cpython-314-x86_64-linux-gnu.so
sosfilt/filter_design.py
sosfilt/sosfilt.py
sosfilt-1.4.1.dist-info/LICENSE
sosfilt-1.4.1.dist-info/METADATA
sosfilt-1.4.1.dist-info/WHEEL
sosfilt-1.4.1.dist-info/RECORD
