Metadata-Version: 2.1
Name: sosfilt
Version: 1.4.1
Summary: Second-order section filtering with multiple filters
Author-Email: Angus Gibson <angus@agibson.me>
License: MIT License
Classifier: Programming Language :: Python :: 3
Classifier: License :: OSI Approved :: MIT License
Classifier: Operating System :: POSIX
Project-URL: homepage, https://github.com/angus-g/sosfilt
Requires-Python: >=3.9
Requires-Dist: scipy
